plasticity_ai/__init__.py
plasticity_ai/__main__.py
plasticity_ai/ai.py
plasticity_ai/util.py
plasticity_ai/assets/index.html
plasticity_ai/assets/css/bootstrap-grid.min.css
plasticity_ai/assets/css/bootstrap-reboot.min.css
plasticity_ai/assets/css/bootstrap.min.css
plasticity_ai/assets/css/main.css
plasticity_ai/assets/icon/MaterialIcons-Regular.eot
plasticity_ai/assets/icon/MaterialIcons-Regular.ijmap
plasticity_ai/assets/icon/MaterialIcons-Regular.svg
plasticity_ai/assets/icon/MaterialIcons-Regular.ttf
plasticity_ai/assets/icon/MaterialIcons-Regular.woff
plasticity_ai/assets/icon/MaterialIcons-Regular.woff2
plasticity_ai/assets/icon/README.md
plasticity_ai/assets/icon/codepoints
plasticity_ai/assets/icon/material-icons.css
plasticity_ai/assets/scripts/bootstrap.min.js
plasticity_ai/assets/scripts/bundle.js
plasticity_ai/assets/scripts/jquery-3.4.1.min.js
plasticity_ai/assets/scripts/popper.min.js
plasticity_ai/resources/aidef.json
plasticity_ai/resources/hashes.json
plasticity_ai/resources/jpen.json
plasticity_ai-0.5.3.dist-info/LICENSE
plasticity_ai-0.5.3.dist-info/METADATA
plasticity_ai-0.5.3.dist-info/WHEEL
plasticity_ai-0.5.3.dist-info/entry_points.txt
plasticity_ai-0.5.3.dist-info/top_level.txt
plasticity_ai-0.5.3.dist-info/RECORD
