Metadata-Version: 2.1
Name: plasticity-ai
Version: 0.5.3
Summary: An AI program editor for The Legend of Zelda: Breath of the Wild
Home-page: https://github.com/NiceneNerd/Plasticity/
Author: NiceneNerd
Author-email: macadamiadaze@gmail.com
License: UNKNOWN
Platform: UNKNOWN
Classifier: Development Status :: 4 - Beta
Classifier: License :: OSI Approved :: GNU General Public License v3 or later (GPLv3+)
Classifier: Programming Language :: Python :: 3.7
Requires-Python: >=3.7
Requires-Dist: aamp
Requires-Dist: oead (>=1.1.6)
Requires-Dist: pywebview
Provides-Extra: cef
Requires-Dist: cefpython3 (>=66.0) ; extra == 'cef'
